TEToolkit/Common.py
TEToolkit/Constants.py
TEToolkit/EMAlgorithm.py
TEToolkit/GeneFeatures.py
TEToolkit/IntervalTree.py
TEToolkit/Normalization.py
TEToolkit/Prob.py
TEToolkit/TEindex.py
TEToolkit/__init__.py
TEToolkit/IO/FeatIO.py
TEToolkit/IO/FeatIO.pyc
TEToolkit/IO/ReadInputs.py
TEToolkit/IO/ReadInputs.pyc
TEToolkit/IO/__init__.py
TEToolkit/IO/__init__.pyc
TEToolkit/ShortRead/ParseBEDFile.py
TEToolkit/ShortRead/ParseBEDFile.pyc
TEToolkit/ShortRead/__init__.py
TEToolkit/ShortRead/__init__.pyc
TEtranscripts-2.0.4.data/scripts/TEcount
TEtranscripts-2.0.4.data/scripts/TEtranscripts
TEtranscripts-2.0.4.dist-info/DESCRIPTION.rst
TEtranscripts-2.0.4.dist-info/METADATA
TEtranscripts-2.0.4.dist-info/RECORD
TEtranscripts-2.0.4.dist-info/WHEEL
TEtranscripts-2.0.4.dist-info/metadata.json
TEtranscripts-2.0.4.dist-info/top_level.txt
