Metadata-Version: 2.0
Name: TEtranscripts
Version: 2.0.4
Summary: Tools for estimating differential enrichment of Transposable Elements and other highly repetitive regions
Home-page: http://hammelllab.labsites.cshl.edu/software#TEtranscripts
Author: Ying Jin, Eric Paniagua, Oliver Tam, Molly Hammell
Author-email: yjin@cshl.edu
License: GPLv3
Keywords: TE transposable element differential enrichment
Platform: Linux
Platform: MacOS
Classifier: Development Status :: 5 - Production/Stable
Classifier: Intended Audience :: Science/Research
Classifier: Environment :: Console
Classifier: Natural Language :: English
Classifier: License :: OSI Approved :: GNU General Public License v3 (GPLv3)
Classifier: Topic :: Scientific/Engineering :: Bio-Informatics
Classifier: Programming Language :: Python :: 2.7
Classifier: Operating System :: MacOS
Classifier: Operating System :: Unix
Requires-Dist: argparse
Requires-Dist: pysam (>=0.9)
